django_serializer/__init__.py
django_serializer/apps.py
django_serializer/base_views.py
django_serializer/exceptions.py
django_serializer/mixins.py
django_serializer/paginator.py
django_serializer/permissions.py
django_serializer/form/__init__.py
django_serializer/form/fields.py
django_serializer/model/__init__.py
django_serializer/model/base.py
django_serializer/serializer/__init__.py
django_serializer/serializer/base.py
django_serializer/serializer/fields.py
django_serializer/v2/__init__.py
django_serializer/v2/parsers.py
django_serializer/v2/renderers.py
django_serializer/v2/serializer.py
django_serializer/v2/serializer_fields.py
django_serializer/v2/settings.py
django_serializer/v2/exceptions/__init__.py
django_serializer/v2/exceptions/base.py
django_serializer/v2/exceptions/conf.py
django_serializer/v2/exceptions/http.py
django_serializer/v2/exceptions/parser.py
django_serializer/v2/swagger/__init__.py
django_serializer/v2/swagger/base.py
django_serializer/v2/swagger/utils.py
django_serializer/v2/swagger/views.py
django_serializer/v2/views/__init__.py
django_serializer/v2/views/base.py
django_serializer/v2/views/generics.py
django_serializer/v2/views/meta.py
django_serializer/v2/views/mixins.py
django_serializer/v2/views/paginator.py
django_serializer-1.2.1.dist-info/LICENSE.txt
django_serializer-1.2.1.dist-info/METADATA
django_serializer-1.2.1.dist-info/WHEEL
django_serializer-1.2.1.dist-info/top_level.txt
django_serializer-1.2.1.dist-info/RECORD
